<annotation>
	<folder>SignsFY2019ImageryCropped</folder>
	<filename>42_N.png</filename>
	<path>/Users/SusanneGov/Documents/Python Projects/Signs-and-Markings-Projects/OverheadSigns/SignsFY2019ImageryCropped/42_N.png</path>
	<source>
		<database>Unknown</database>
	</source>
	<size>
		<width>560</width>
		<height>280</height>
		<depth>3</depth>
	</size>
	<segmented>0</segmented>
	<object>
		<name>no left turn sign</name>
		<pose>Unspecified</pose>
		<truncated>0</truncated>
		<difficult>0</difficult>
		<bndbox>
			<xmin>182</xmin>
			<ymin>32</ymin>
			<xmax>201</xmax>
			<ymax>53</ymax>
		</bndbox>
	</object>
	<object>
		<name>street name sign</name>
		<pose>Unspecified</pose>
		<truncated>0</truncated>
		<difficult>0</difficult>
		<bndbox>
			<xmin>211</xmin>
			<ymin>33</ymin>
			<xmax>241</xmax>
			<ymax>53</ymax>
		</bndbox>
	</object>
	<object>
		<name>no right turn sign</name>
		<pose>Unspecified</pose>
		<truncated>0</truncated>
		<difficult>0</difficult>
		<bndbox>
			<xmin>285</xmin>
			<ymin>36</ymin>
			<xmax>304</xmax>
			<ymax>58</ymax>
		</bndbox>
	</object>
	<object>
		<name>dont block the box sign</name>
		<pose>Unspecified</pose>
		<truncated>0</truncated>
		<difficult>0</difficult>
		<bndbox>
			<xmin>313</xmin>
			<ymin>26</ymin>
			<xmax>338</xmax>
			<ymax>68</ymax>
		</bndbox>
	</object>
</annotation>
